{
  "sorte": [
    { "id": 1,  "texto": "Ganhe R$ 500 do banco.",                                              "tipo": "ganhar_dinheiro",   "valor": 500  },
    { "id": 2,  "texto": "Receba R$ 200 de cada jogador.",                                      "tipo": "receber_jogadores", "valor": 200  },
    { "id": 3,  "texto": "Dividendos de ações: ganhe R$ 1.000.",                                "tipo": "ganhar_dinheiro",   "valor": 1000 },
    { "id": 4,  "texto": "Prêmio de beleza do bairro: ganhe R$ 150.",                           "tipo": "ganhar_dinheiro",   "valor": 150  },
    { "id": 5,  "texto": "Reembolso de imposto de renda: ganhe R$ 750.",                        "tipo": "ganhar_dinheiro",   "valor": 750  },
    { "id": 6,  "texto": "Herança inesperada: ganhe R$ 2.000.",                                 "tipo": "ganhar_dinheiro",   "valor": 2000 },
    { "id": 7,  "texto": "Venda de artesanato: ganhe R$ 300.",                                  "tipo": "ganhar_dinheiro",   "valor": 300  },
    { "id": 8,  "texto": "Prêmio de loteria: ganhe R$ 1.500.",                                  "tipo": "ganhar_dinheiro",   "valor": 1500 },
    { "id": 9,  "texto": "Consultoria freelance bem-sucedida: ganhe R$ 600.",                   "tipo": "ganhar_dinheiro",   "valor": 600  },
    { "id": 10, "texto": "Bônus de fim de ano: ganhe R$ 800.",                                  "tipo": "ganhar_dinheiro",   "valor": 800  },
    { "id": 11, "texto": "Receba R$ 100 de cada jogador como presente de aniversário.",         "tipo": "receber_jogadores", "valor": 100  },
    { "id": 12, "texto": "Cada jogador te paga R$ 250 por um empréstimo antigo.",               "tipo": "receber_jogadores", "valor": 250  },
    { "id": 13, "texto": "Você ganhou uma aposta: receba R$ 150 de cada jogador.",              "tipo": "receber_jogadores", "valor": 150  },
    { "id": 14, "texto": "Sorte! Ganhe uma carta 'Saia da Prisão'.",                            "tipo": "carta_prisao",      "valor": 0    },
    { "id": 15, "texto": "Promoção no trabalho: ganhe R$ 900.",                                 "tipo": "ganhar_dinheiro",   "valor": 900  },
    { "id": 16, "texto": "Você encontrou uma carteira perdida e foi recompensado: ganhe R$ 400.","tipo": "ganhar_dinheiro",  "valor": 400  },
    { "id": 17, "texto": "Investimento em startup deu retorno: ganhe R$ 2.500.",                "tipo": "ganhar_dinheiro",   "valor": 2500 },
    { "id": 18, "texto": "Receba R$ 350 de aluguel retroativo.",                                "tipo": "ganhar_dinheiro",   "valor": 350  },
    { "id": 19, "texto": "Prêmio de concurso cultural: ganhe R$ 700.",                          "tipo": "ganhar_dinheiro",   "valor": 700  },
    { "id": 20, "texto": "Venda de carro usado: ganhe R$ 1.200.",                               "tipo": "ganhar_dinheiro",   "valor": 1200 },
    { "id": 21, "texto": "Cachê por participação em pesquisa: ganhe R$ 250.",                   "tipo": "ganhar_dinheiro",   "valor": 250  },
    { "id": 22, "texto": "Receba R$ 500 de cada jogador como parcela de negócio.",              "tipo": "receber_jogadores", "valor": 500  },
    { "id": 23, "texto": "Patrocínio de evento local: ganhe R$ 1.100.",                         "tipo": "ganhar_dinheiro",   "valor": 1100 },
    { "id": 24, "texto": "Prêmio de inovação: ganhe R$ 1.800.",                                 "tipo": "ganhar_dinheiro",   "valor": 1800 },
    { "id": 25, "texto": "Recebeu gorjetas acumuladas: ganhe R$ 180.",                          "tipo": "ganhar_dinheiro",   "valor": 180  },
    { "id": 26, "texto": "Venda de ações com lucro: ganhe R$ 1.400.",                           "tipo": "ganhar_dinheiro",   "valor": 1400 },
    { "id": 27, "texto": "Receba R$ 300 de cada jogador por consultoria.",                      "tipo": "receber_jogadores", "valor": 300  },
    { "id": 28, "texto": "Descoberta de tesouro em reforma: ganhe R$ 3.000.",                   "tipo": "ganhar_dinheiro",   "valor": 3000 },
    { "id": 29, "texto": "Reembolso de viagem cancelada: ganhe R$ 650.",                        "tipo": "ganhar_dinheiro",   "valor": 650  },
    { "id": 30, "texto": "Aluguel de espaço para evento: ganhe R$ 950.",                        "tipo": "ganhar_dinheiro",   "valor": 950  },
    { "id": 31, "texto": "Bônus por indicação de cliente: ganhe R$ 450.",                       "tipo": "ganhar_dinheiro",   "valor": 450  },
    { "id": 32, "texto": "Receba R$ 400 de cada jogador por royalties.",                        "tipo": "receber_jogadores", "valor": 400  },
    { "id": 33, "texto": "Prêmio de mérito acadêmico: ganhe R$ 550.",                           "tipo": "ganhar_dinheiro",   "valor": 550  },
    { "id": 34, "texto": "Venda de móveis antigos: ganhe R$ 320.",                              "tipo": "ganhar_dinheiro",   "valor": 320  },
    { "id": 35, "texto": "Cashback acumulado no cartão: ganhe R$ 220.",                         "tipo": "ganhar_dinheiro",   "valor": 220  },
    { "id": 36, "texto": "Receba R$ 600 de cada jogador por dividendos de empresa.",            "tipo": "receber_jogadores", "valor": 600  },
    { "id": 37, "texto": "Reajuste salarial retroativo: ganhe R$ 1.300.",                       "tipo": "ganhar_dinheiro",   "valor": 1300 },
    { "id": 38, "texto": "Participação em reality show: ganhe R$ 2.200.",                       "tipo": "ganhar_dinheiro",   "valor": 2200 },
    { "id": 39, "texto": "Fundo de reserva liberado: ganhe R$ 1.600.",                          "tipo": "ganhar_dinheiro",   "valor": 1600 },
    { "id": 40, "texto": "Doação anônima recebida: ganhe R$ 850.",                              "tipo": "ganhar_dinheiro",   "valor": 850  },
    { "id": 41, "texto": "Receba R$ 50 de cada jogador por coleta de pedágio.",                 "tipo": "receber_jogadores", "valor": 750   },
    { "id": 42, "texto": "Recuperação de crédito em disputa: ganhe R$ 1.050.",                  "tipo": "ganhar_dinheiro",   "valor": 1050 },
    { "id": 43, "texto": "Bônus de produtividade: ganhe R$ 700.",                               "tipo": "ganhar_dinheiro",   "valor": 700  },
    { "id": 44, "texto": "Venda de propriedade digital: ganhe R$ 1.750.",                       "tipo": "ganhar_dinheiro",   "valor": 1750 },
    { "id": 45, "texto": "Receba R$ 350 de cada jogador como taxa de parceria.",                "tipo": "receber_jogadores", "valor": 350  },
    { "id": 46, "texto": "Prêmio surpresa: ganhe R$ 1.250.",                                   "tipo": "ganhar_dinheiro",   "valor": 1250 },
    { "id": 47, "texto": "Retorno de seguro de vida: ganhe R$ 2.800.",                          "tipo": "ganhar_dinheiro",   "valor": 2800 },
    { "id": 48, "texto": "Encontrou dinheiro esquecido na conta poupança: ganhe R$ 420.",       "tipo": "ganhar_dinheiro",   "valor": 420  },
    { "id": 49, "texto": "Recompensa por denúncia de fraude: ganhe R$ 980.",                    "tipo": "ganhar_dinheiro",   "valor": 980  },
    { "id": 50, "texto": "Sorte absoluta! Ganhe R$ 5.000 do banco.",                            "tipo": "ganhar_dinheiro",   "valor": 5000 }
  ],
  "reves": [
    { "id": 1,  "texto": "Pague R$ 300 de multa de trânsito.",                                  "tipo": "perder_dinheiro",   "valor": 300  },
    { "id": 2,  "texto": "Pague R$ 150 para cada jogador.",                                     "tipo": "pagar_jogadores",   "valor": 150  },
    { "id": 3,  "texto": "Vá para a Prisão.",                                                   "tipo": "prisao",            "valor": 0    },
    { "id": 4,  "texto": "Vazamento na encanação: pague R$ 600 de reparo.",                     "tipo": "perder_dinheiro",   "valor": 600  },
    { "id": 5,  "texto": "Multa por infração fiscal: pague R$ 1.000.",                          "tipo": "perder_dinheiro",   "valor": 1000 },
    { "id": 6,  "texto": "Acidente de carro: pague R$ 1.500 de franquia.",                      "tipo": "perder_dinheiro",   "valor": 1500 },
    { "id": 7,  "texto": "Pague R$ 200 de cada jogador por dívida antiga.",                     "tipo": "pagar_jogadores",   "valor": 200  },
    { "id": 8,  "texto": "Reforma emergencial no telhado: pague R$ 800.",                       "tipo": "perder_dinheiro",   "valor": 800  },
    { "id": 9,  "texto": "Processo judicial perdido: pague R$ 2.000.",                          "tipo": "perder_dinheiro",   "valor": 2000 },
    { "id": 10, "texto": "Imposto predial atrasado: pague R$ 750.",                             "tipo": "perder_dinheiro",   "valor": 750  },
    { "id": 11, "texto": "Pague R$ 100 para cada jogador por aposta perdida.",                  "tipo": "pagar_jogadores",   "valor": 100  },
    { "id": 12, "texto": "Internação hospitalar: pague R$ 1.200.",                              "tipo": "perder_dinheiro",   "valor": 1200 },
    { "id": 13, "texto": "Furto de pertences: pague R$ 500.",                                   "tipo": "perder_dinheiro",   "valor": 500  },
    { "id": 14, "texto": "Multa de condomínio por barulho: pague R$ 250.",                      "tipo": "perder_dinheiro",   "valor": 250  },
    { "id": 15, "texto": "Pague R$ 300 para cada jogador por acordão de negócio.",              "tipo": "pagar_jogadores",   "valor": 300  },
    { "id": 16, "texto": "Rescisão contratual com multa: pague R$ 1.800.",                      "tipo": "perder_dinheiro",   "valor": 1800 },
    { "id": 17, "texto": "Falha no investimento: pague R$ 2.500.",                              "tipo": "perder_dinheiro",   "valor": 2500 },
    { "id": 18, "texto": "Devolução de pagamento indevido: pague R$ 650.",                      "tipo": "perder_dinheiro",   "valor": 650  },
    { "id": 19, "texto": "Conserto emergencial do elevador: pague R$ 900.",                     "tipo": "perder_dinheiro",   "valor": 900  },
    { "id": 20, "texto": "Pague R$ 400 para cada jogador por perda de contrato.",               "tipo": "pagar_jogadores",   "valor": 400  },
    { "id": 21, "texto": "Dívida de cartão de crédito: pague R$ 1.100.",                        "tipo": "perder_dinheiro",   "valor": 1100 },
    { "id": 22, "texto": "Multa ambiental: pague R$ 700.",                                      "tipo": "perder_dinheiro",   "valor": 700  },
    { "id": 23, "texto": "Pague R$ 250 para cada jogador por vistoria de imóvel.",              "tipo": "pagar_jogadores",   "valor": 250  },
    { "id": 24, "texto": "Despesa com advogado: pague R$ 1.400.",                               "tipo": "perder_dinheiro",   "valor": 1400 },
    { "id": 25, "texto": "Obra de calçada obrigatória: pague R$ 480.",                          "tipo": "perder_dinheiro",   "valor": 480  },
    { "id": 26, "texto": "Conta de energia atrasada com juros: pague R$ 320.",                  "tipo": "perder_dinheiro",   "valor": 320  },
    { "id": 27, "texto": "Pague R$ 500 para cada jogador por dividendos devidos.",              "tipo": "pagar_jogadores",   "valor": 500  },
    { "id": 28, "texto": "Reparo urgente no sistema elétrico: pague R$ 950.",                   "tipo": "perder_dinheiro",   "valor": 950  },
    { "id": 29, "texto": "Voo perdido com multa de remarcação: pague R$ 550.",                  "tipo": "perder_dinheiro",   "valor": 550  },
    { "id": 30, "texto": "Auditoria fiscal com penalidade: pague R$ 2.200.",                    "tipo": "perder_dinheiro",   "valor": 2200 },
    { "id": 31, "texto": "Pague R$ 350 para cada jogador por taxa de liquidação.",              "tipo": "pagar_jogadores",   "valor": 350  },
    { "id": 32, "texto": "Inundação no imóvel: pague R$ 1.600.",                                "tipo": "perder_dinheiro",   "valor": 1600 },
    { "id": 33, "texto": "Cancelamento de contrato com multa: pague R$ 850.",                   "tipo": "perder_dinheiro",   "valor": 850  },
    { "id": 34, "texto": "Dedetização emergencial: pague R$ 280.",                              "tipo": "perder_dinheiro",   "valor": 280  },
    { "id": 35, "texto": "Pague R$ 600 para cada jogador por parcela de consórcio.",            "tipo": "pagar_jogadores",   "valor": 600  },
    { "id": 36, "texto": "Vazamento de gás com interdição: pague R$ 1.300.",                    "tipo": "perder_dinheiro",   "valor": 1300 },
    { "id": 37, "texto": "Perda de bagagem em viagem: pague R$ 420.",                           "tipo": "perder_dinheiro",   "valor": 420  },
    { "id": 38, "texto": "Multa por obra irregular: pague R$ 1.050.",                           "tipo": "perder_dinheiro",   "valor": 1050 },
    { "id": 39, "texto": "Pague R$ 50 para cada jogador por taxa de condomínio extra.",         "tipo": "pagar_jogadores",   "valor": 50   },
    { "id": 40, "texto": "Descumprimento de prazo contratual: pague R$ 1.750.",                 "tipo": "perder_dinheiro",   "valor": 1750 },
    { "id": 41, "texto": "Dano a terceiros em acidente: pague R$ 980.",                         "tipo": "perder_dinheiro",   "valor": 980  },
    { "id": 42, "texto": "Pague R$ 450 para cada jogador por quebra de acordo.",                "tipo": "pagar_jogadores",   "valor": 450  },
    { "id": 43, "texto": "Substituição emergencial de encanamento: pague R$ 730.",              "tipo": "perder_dinheiro",   "valor": 730  },
    { "id": 44, "texto": "Golpe em investimento: pague R$ 3.000.",                              "tipo": "perder_dinheiro",   "valor": 2000 },
    { "id": 45, "texto": "Pague R$ 200 para cada jogador por multa coletiva.",                  "tipo": "pagar_jogadores",   "valor": 200  },
    { "id": 46, "texto": "Devolução de produto com prejuízo: pague R$ 360.",                    "tipo": "perder_dinheiro",   "valor": 360  },
    { "id": 47, "texto": "Embargo de obra por irregularidade: pague R$ 1.900.",                 "tipo": "perder_dinheiro",   "valor": 1900 },
    { "id": 48, "texto": "Fraude bancária descoberta tarde: pague R$ 2.800.",                   "tipo": "perder_dinheiro",   "valor": 2800 },
    { "id": 49, "texto": "Pague R$ 700 para cada jogador por indenização trabalhista.",         "tipo": "pagar_jogadores",   "valor": 700  },
    { "id": 50, "texto": "Catástrofe! Pague R$ 5.000 de dívida inesperada.",                    "tipo": "perder_dinheiro",   "valor": 2500 }
  ]
}